<?xml version="1.0" encoding="UTF-8" ?>
<extension type="package" version="3.4" method="upgrade">
    <name>BootstrapBase Package</name>
    <author>KnowledgeArc Ltd</author>
    <creationDate>2015-08-20</creationDate>
    <packagename>bootstrapbase</packagename>
    <version>1.0.0-dev</version>
    <copyright>>Copyright (C) 2015 KnowledgeArc Ltd. All rights reserved.</copyright>
    <license>http://www.gnu.org/licenses/gpl-3.0.html</license>
    <packager>KnowledgeArc Ltd</packager>
    <packagerurl>http://www.knowledgearc.org</packagerurl>
    <description>BootstrapBase bootstrapified template and accompanying plugin.</description>

    <files folder="packages">
        <file type="plugin" id="bootstrapbase" group="editors-xtd">plg_system_bootstrapbase.zip</file>
        <file type="template" id="bootstrapbase" client="site">tpl_bootstrapbase.zip</file>
    </files>
</extension>